batches_n_more/__init__.py
batches_n_more/align_pt.py
batches_n_more/clique_mediator.py
batches_n_more/example_detailed.py
batches_n_more/example_short.py
batches_n_more/linear_regression.py
batches_n_more/peaktable.py
batches_n_more/peaktable_align.py
batches_n_more/pt_helper.py
batches_n_more/pt_io.py
batches_n_more/similarity_func.py
batches_n_more-1.0.0.dist-info/LICENSE
batches_n_more-1.0.0.dist-info/METADATA
batches_n_more-1.0.0.dist-info/WHEEL
batches_n_more-1.0.0.dist-info/top_level.txt
batches_n_more-1.0.0.dist-info/RECORD
