Metadata-Version: 2.1
Name: batches-n-more
Version: 1.0.0
Summary: Align feature tables from multiple GC/LC-MS batches into one feature table and correct for batch effects
Author-email: Lukas Gessl <lukas.gessl@icloud.com>
Classifier: Programming Language :: Python :: 3
Classifier: License :: OSI Approved :: MIT License
Classifier: Operating System :: OS Independent
Requires-Python: >=3.9
License-File: LICENSE
Requires-Dist: numpy (>=1.21.1)
Requires-Dist: scipy (>=1.7.0)
Requires-Dist: scikit-learn (>=0.24.2)
Requires-Dist: pandas (>=1.3.1)
Requires-Dist: typing-extensions (>=4.3.0)
Requires-Dist: plotnine (>=0.8.0)
Requires-Dist: networkx (>=2.6.2)
Requires-Dist: openpyxl (>=3.0.10)
